[
  {
    "id": "001",
    "name": "001",
    "file": "001.md"
  },
  {
    "id": "002",
    "name": "002",
    "file": "002.md"
  },
  {
    "id": "003",
    "name": "003",
    "file": "003.md"
  },
  {
    "id": "004",
    "name": "004",
    "file": "004.md"
  },
  {
    "id": "005",
    "name": "005",
    "file": "005.md"
  },
  {
    "id": "006",
    "name": "006",
    "file": "006.md"
  },
  {
    "id": "007",
    "name": "007",
    "file": "007.md"
  },
  {
    "id": "008",
    "name": "008",
    "file": "008.md"
  },
  {
    "id": "009",
    "name": "009",
    "file": "009.md"
  },
  {
    "id": "010",
    "name": "010",
    "file": "010.md"
  },
  {
    "id": "011",
    "name": "011",
    "file": "011.md"
  },
  {
    "id": "012",
    "name": "012",
    "file": "012.md"
  },
  {
    "id": "013",
    "name": "013",
    "file": "013.md"
  },
  {
    "id": "014",
    "name": "014",
    "file": "014.md"
  },
  {
    "id": "015",
    "name": "015",
    "file": "015.md"
  },
  {
    "id": "016",
    "name": "016",
    "file": "016.md"
  },
  {
    "id": "017",
    "name": "017",
    "file": "017.md"
  },
  {
    "id": "018",
    "name": "018",
    "file": "018.md"
  },
  {
    "id": "019",
    "name": "019",
    "file": "019.md"
  },
  {
    "id": "020",
    "name": "020",
    "file": "020.md"
  },
  {
    "id": "021",
    "name": "021",
    "file": "021.md"
  },
  {
    "id": "022",
    "name": "022",
    "file": "022.md"
  },
  {
    "id": "023",
    "name": "023",
    "file": "023.md"
  },
  {
    "id": "024",
    "name": "024",
    "file": "024.md"
  },
  {
    "id": "025",
    "name": "025",
    "file": "025.md"
  }
]
